excelstyler/__init__.py
excelstyler/chart.py
excelstyler/headers.py
excelstyler/helpers.py
excelstyler/styles.py
excelstyler/to_locale_string.py
excelstyler/utils.py
excelstyler/values.py
excelstyler-0.1.1.dist-info/METADATA
excelstyler-0.1.1.dist-info/WHEEL
excelstyler-0.1.1.dist-info/licenses/LICENSE
excelstyler-0.1.1.dist-info/RECORD
