Metadata-Version: 2.4
Name: excelstyler
Version: 0.1.1
Summary: Style and format Excel files easily with openpyxl
Project-URL: Homepage, https://github.com/7nimor/excelstyler
Author-email: Nima Orangi <7nimor@gmail.com>
License: GNU AFFERO GENERAL PUBLIC LICENSE
License-File: LICENSE
Keywords: excel,openpyxl,spreadsheet,styling,xlsx
Classifier: License :: OSI Approved :: MIT License
Classifier: Operating System :: OS Independent
Classifier: Programming Language :: Python :: 3
Requires-Python: >=3.8
Requires-Dist: jdatetime>=4.1.0
Requires-Dist: openpyxl>=3.0.10
